ytdx.py
ytdx-1.0.0.dist-info/licenses/LICENSE
ytdx-1.0.0.dist-info/METADATA
ytdx-1.0.0.dist-info/WHEEL
ytdx-1.0.0.dist-info/entry_points.txt
ytdx-1.0.0.dist-info/top_level.txt
ytdx-1.0.0.dist-info/RECORD
