Metadata-Version: 2.4
Name: ytdx
Version: 1.0.0
Summary: YouTube video downloader via command line
Home-page: https://github.com/Flaymie/ytdx
Author: Flaymie
Author-email: Flaymie <funquenop@gmail.com>
License: MIT
Project-URL: Homepage, https://github.com/Flaymie/ytdx
Classifier: Programming Language :: Python :: 3
Classifier: License :: OSI Approved :: MIT License
Classifier: Operating System :: OS Independent
Requires-Python: >=3.6
License-File: LICENSE
Requires-Dist: yt-dlp
Dynamic: author
Dynamic: home-page
Dynamic: license-file
Dynamic: requires-python
